cardpydentity/__init__.py
cardpydentity/fuzzy.py
cardpydentity/gpt.py
cardpydentity/helpers.py
cardpydentity/load.py
cardpydentity/matcher.py
cardpydentity-0.2.0.dist-info/LICENSE
cardpydentity-0.2.0.dist-info/METADATA
cardpydentity-0.2.0.dist-info/WHEEL
cardpydentity-0.2.0.dist-info/top_level.txt
cardpydentity-0.2.0.dist-info/RECORD
